paramax_py39/__init__.py
paramax_py39/py.typed
paramax_py39/utils.py
paramax_py39/wrappers.py
paramax_py39-0.0.3.1.dist-info/WHEEL
paramax_py39-0.0.3.1.dist-info/METADATA
paramax_py39-0.0.3.1.dist-info/RECORD
