Metadata-Version: 2.4
Name: paramax-py39
Version: 0.0.3.1
Summary: Parameterizations and parameter constraints for JAX PyTrees, forked for Python 3.9 compatability.
Keywords: jax,neural-networks,equinox
Author: Joshua Chen
Author-email: Joshua Chen <joshuawchen@icloud.com>
License-Expression: MIT
Requires-Dist: jax
Requires-Dist: equinox
Requires-Dist: jaxtyping
Requires-Dist: pytest ; extra == 'dev'
Requires-Dist: beartype ; extra == 'dev'
Requires-Dist: ruff ; extra == 'dev'
Requires-Dist: sphinx ; extra == 'dev'
Requires-Dist: sphinx-book-theme ; extra == 'dev'
Requires-Dist: sphinx-copybutton ; extra == 'dev'
Requires-Dist: sphinx-autodoc-typehints ; extra == 'dev'
Requires-Python: >=3.9
Project-URL: repository, https://github.com/joshuawchen/paramax_py39
Provides-Extra: dev
